{
    "configurations": [
        {
            "name": "Win32",
            "includePath": [
                "${workspaceFolder}/**",
                "C:/raylib/raylib/src"
            ],
            "defines": [
                "_DEBUG",
                "UNICODE",
                "_UNICODE"
            ],
            "windowsSdkVersion": "10.0.22621.0",
            "compilerPath": "cl.exe",
            "cStandard": "c23",
            "cppStandard": "c++23",
            "intelliSenseMode": "${default}",
            "mergeConfigurations": true,
            "browse": {
                "limitSymbolsToIncludedHeaders": true,
                "path": [
                    "C:/raylib/raylib/src"
                ]
            }
        }
    ],
    "version": 4
}